cloudtoken_plugin/__init__.py
cloudtoken_plugin/okta.py
cloudtoken_plugin.okta-0.0.9.dist-info/DESCRIPTION.rst
cloudtoken_plugin.okta-0.0.9.dist-info/LICENSE.txt
cloudtoken_plugin.okta-0.0.9.dist-info/METADATA
cloudtoken_plugin.okta-0.0.9.dist-info/RECORD
cloudtoken_plugin.okta-0.0.9.dist-info/WHEEL
cloudtoken_plugin.okta-0.0.9.dist-info/metadata.json
cloudtoken_plugin.okta-0.0.9.dist-info/top_level.txt
