Metadata-Version: 2.0
Name: cloudtoken-plugin.okta
Version: 0.0.9
Summary: OKTA plugin for cloudtoken.
Home-page: https://bitbucket.org/atlassian/cloudtoken
Author: Andy Loughran
Author-email: andy@lockran.com
License: Apache
Platform: UNKNOWN
Requires-Python: >=3.5
Requires-Dist: cloudtoken (>=0.0.1)
Requires-Dist: requests (>=2.18.4)
Requires-Dist: bs4 (>=0.0.1)
